covidxai/__init__.py
covidxai/explainability/__init__.py
covidxai/explainability/gradcam/__init__.py
covidxai/explainability/gradcam/grad-cam.py
covidxai/explainability/gradcam/gradcam.py
covidxai/explainability/gradcam/torch_gradcam.py
covidxai/explainability/lime/__init__.py
covidxai/explainability/lime/contrastive_lime.py
covidxai/explainability/lime/lime.py
covidxai/explainability/lime/torch_lime.py
covidxai/explainability/lrp/__init__.py
covidxai/explainability/lrp/contrastive_lrp.py
covidxai/explainability/lrp/lrp.py
covidxai/explainability/lrp/lrp_utils.py
covidxai/model/__init__.py
covidxai/model/config.py
covidxai/model/data_loader.py
covidxai/model/evaluate.py
covidxai/model/models.py
covidxai/model/train.py
covidxai/model/u_mnist.py
covidxai/model/unet.py
covidxai/model/utils.py
covidxai-0.1.2.dist-info/LICENSE
covidxai-0.1.2.dist-info/METADATA
covidxai-0.1.2.dist-info/WHEEL
covidxai-0.1.2.dist-info/top_level.txt
covidxai-0.1.2.dist-info/RECORD
