Metadata-Version: 2.1
Name: covidxai
Version: 0.1.2
Summary: Using XAI algorithms on Computer Vision models to explain predictions.
Home-page: https://github.com/samsonq/COVID-XAI
Author: Samson Qian
Author-email: samsonqian@gmail.com
License: MIT
Keywords: computer-vision explainable-ai lime torch_lrp grad-cam covid-19 pneumonia-detection
Platform: UNKNOWN
Requires-Python: >=3.6
